pythonproject2021/__init__.py
pythonproject2021/test.py
pythonproject2021-0.2.3.dist-info/LICENSE.txt
pythonproject2021-0.2.3.dist-info/METADATA
pythonproject2021-0.2.3.dist-info/WHEEL
pythonproject2021-0.2.3.dist-info/top_level.txt
pythonproject2021-0.2.3.dist-info/RECORD
