Metadata-Version: 2.1
Name: pythonproject2021
Version: 0.2.3
Summary: Useful tools to work with Elastic stack in Python
Home-page: UNKNOWN
Author: UNKNOWN
Author-email: UNKNOWN
License: MIT
Keywords: Elastic,ElasticSearch,Elastic Stack,Python 3,Elastic 7
Platform: UNKNOWN
